MorseCodePy/__init__.py
MorseCodePy/chart.py
MorseCodePy/decode.py
MorseCodePy/encode.py
MorseCodePy/play_pygame.py
MorseCodePy/play_sounddevice.py
MorseCodePy/setup_logging.py
MorseCodePy/utilities.py
MorseCodePy/codes/decodes.json
MorseCodePy/codes/encodes.json
MorseCodePy/sounds/dash.wav
MorseCodePy/sounds/dot.wav
MorseCodePy/sounds/error.wav
morsecodepy-3.8.dist-info/WHEEL
morsecodepy-3.8.dist-info/METADATA
morsecodepy-3.8.dist-info/RECORD
