Metadata-Version: 2.1
Name: MorseCodePy
Version: 3.8
Summary: Encode, decode & play Morse code easily
Author-email: CrazyFlyKite <karpenkoartem2846@gmail.com>
Requires-Python: >=3.11
Classifier: Intended Audience :: Developers
Classifier: License :: OSI Approved :: MIT License
Classifier: Programming Language :: Python :: 3.10
Classifier: Programming Language :: Python :: 3.11
Classifier: Programming Language :: Python :: 3.12
Classifier: Topic :: Utilities
Requires-Dist: pygame>=2.5.2
Requires-Dist: sounddevice>=0.4.6
Requires-Dist: soundfile>=0.12.1
Requires-Dist: numpy>=1.26.4
Project-URL: Download, https://pypi.org/project/MorseCodePy
Project-URL: Repository, https://github.com/CrazyFlyKite/MorseCodePy
Project-URL: Tracker, https://github.com/CrazyFlyKite/MorseCodePy/issues
